[{
	"img": "/static/img/house2.jpg",
	"place": "崇明县",
	"title": "我最爱这个美丽而又富饶的地方了",
	"head": "/static/img/head.jpg",
	"zan": 33,
	"comment": 4,
	"href": "/s1"
},
{
	"img": "/static/img/house3.jpg",
	"place": "崇明县",
	"title": "我最爱这个美丽而又富饶的地方了",
	"head": "/static/img/head.jpg",
	"zan": 33,
	"comment": 4,
	"href": "/s2"
},
{
	"img": "/static/img/house5.jpg",
	"place": "崇明县",
	"title": "我最爱这个美丽而又富饶的地方了",
	"head": "/static/img/head.jpg",
	"zan": 33,
	"comment": 4,
	"href": "/s3"
},
{
	"img": "/static/img/house4.jpg",
	"place": "崇明县",
	"title": "我最爱这个美丽而又富饶的地方了",
	"head": "/static/img/head.jpg",
	"zan": 33,
	"comment": 4,
	"href": "/s1"
},
{
	"img": "/static/img/house6.jpg",
	"place": "崇明县",
	"title": "我最爱这个美丽而又富饶的地方了",
	"head": "/static/img/head.jpg",
	"zan": 33,
	"comment": 4,
	"href": "/s2"
},
{
	"img": "/static/img/house7.jpg",
	"place": "崇明县",
	"title": "我最爱这个美丽而又富饶的地方了",
	"head": "/static/img/head.jpg",
	"zan": 33,
	"comment": 4,
	"href": "/s3"
},
{
	"img": "/static/img/house8.jpg",
	"place": "崇明县",
	"title": "我最爱这个美丽而又富饶的地方了",
	"head": "/static/img/head.jpg",
	"zan": 33,
	"comment": 4,
	"href": "/s1"
},
{
	"img": "/static/img/house2.jpg",
	"place": "崇明县",
	"title": "我最爱这个美丽而又富饶的地方了",
	"head": "/static/img/head.jpg",
	"zan": 33,
	"comment": 4,
	"href": "/s1"
},
{
	"img": "/static/img/house2.jpg",
	"place": "崇明县",
	"title": "我最爱这个美丽而又富饶的地方了",
	"head": "/static/img/head.jpg",
	"zan": 33,
	"comment": 4,
	"href": "/s1"
},
{
	"img": "/static/img/house2.jpg",
	"place": "崇明县",
	"title": "我最爱这个美丽而又富饶的地方了",
	"head": "/static/img/head.jpg",
	"zan": 33,
	"comment": 4,
	"href": "/s4"
}]